new_pytest_needle/__init__.py
new_pytest_needle/driver.py
new_pytest_needle/exceptions.py
new_pytest_needle/engines/__init__.py
new_pytest_needle/engines/base.py
new_pytest_needle/engines/imagemagick_engine.py
new_pytest_needle/engines/perceptualdiff_engine.py
new_pytest_needle/engines/pil_engine.py
new_pytest_needle-0.1.3.dist-info/LICENSE
new_pytest_needle-0.1.3.dist-info/METADATA
new_pytest_needle-0.1.3.dist-info/WHEEL
new_pytest_needle-0.1.3.dist-info/top_level.txt
new_pytest_needle-0.1.3.dist-info/RECORD
