Metadata-Version: 2.1
Name: new-pytest-needle
Version: 0.1.3
Summary: VT pytest + selenium
Home-page: https://github.com/Gadzillion/new_pytest_needle
Author: P.Serega
Author-email: serjojo1@gmail.com
License: MIT
Keywords: pytest-needle,imagemagick,VT
Platform: UNKNOWN
Classifier: Development Status :: 1 - Planning
Classifier: Framework :: Pytest
Classifier: Intended Audience :: Science/Research
Classifier: Natural Language :: English
Classifier: License :: OSI Approved :: BSD License
Classifier: Operating System :: POSIX :: Linux
Classifier: Operating System :: Microsoft :: Windows
Classifier: Operating System :: MacOS :: MacOS X
Classifier: Programming Language :: Python :: 3.6
Classifier: Programming Language :: Python :: 3.7
Classifier: Programming Language :: Python :: 3.8
Classifier: Topic :: Software Development :: Libraries
Classifier: Topic :: Software Development :: Quality Assurance
Classifier: Topic :: Software Development :: Testing
Classifier: Topic :: Utilities
Requires-Python: >=3.6
Requires-Dist: Pillow
Requires-Dist: pytest
Requires-Dist: pytest-selenium
Requires-Dist: selenium
Requires-Dist: allure-pytest
